{
  "id": "39ac6b36d77c71cbe9d069345612fbb2",
  "platform": "twitter",
  "data": {
    "id": "tweet_AI_8_1763682192",
    "text": "Amazing content about #AI! This is tweet 8.",
    "user": {
      "id": "user_AI_8",
      "username": "user_8",
      "followers_count": 33434
    },
    "created_at": "2025-11-20T18:43:12.538590Z",
    "like_count": 789,
    "retweet_count": 140,
    "reply_count": 88,
    "quote_count": 48,
    "public_metrics": {
      "like_count": 56,
      "retweet_count": 186,
      "reply_count": 66,
      "quote_count": 18
    }
  },
  "scraped_at": "2025-11-20T18:43:12.542937"
}